xharvest/__init__.py
xharvest/auth.py
xharvest/logger.py
xharvest/threads.py
xharvest/tray.py
xharvest/ui.py
xharvest/utils.py
xharvest/data/__init__.py
xharvest/data/css/main.css
xharvest/data/glade/about.glade
xharvest/data/glade/general_preferences.glade
xharvest/data/glade/login.glade
xharvest/data/glade/login_o_auth2.glade
xharvest/data/glade/login_personal_access_token.glade
xharvest/data/glade/main2.glade
xharvest/data/glade/main_headerbar.glade
xharvest/data/glade/main_window.glade
xharvest/data/glade/preferences.glade
xharvest/data/glade/settings.glade
xharvest/data/glade/shortcut_entry.glade
xharvest/data/glade/shortcuts_preferences.glade
xharvest/data/glade/support_preferences.glade
xharvest/data/glade/time_entries.glade
xharvest/data/glade/time_entry.glade
xharvest/data/glade/time_entry_form.glade
xharvest/data/glade/time_summary.glade
xharvest/data/glade/week.glade
xharvest/data/glade/weekday.glade
xharvest/data/img/rubberduck.jpg
xharvest/data/img/xharvest.png
xharvest/handlers/__init__.py
xharvest/handlers/about.py
xharvest/handlers/base.py
xharvest/handlers/general_preferences.py
xharvest/handlers/login.py
xharvest/handlers/login_oauth2.py
xharvest/handlers/login_pat.py
xharvest/handlers/main.py
xharvest/handlers/main_headerbar.py
xharvest/handlers/preferences.py
xharvest/handlers/settings.py
xharvest/handlers/shortcut_entry.py
xharvest/handlers/shortcuts_preferences.py
xharvest/handlers/time_summary.py
xharvest/handlers/timeentries.py
xharvest/handlers/timeentry.py
xharvest/handlers/timeentryform.py
xharvest/handlers/week.py
xharvest/handlers/weekday.py
xharvest/models/__init__.py
xharvest/models/assignments.py
xharvest/models/auth.py
xharvest/models/base.py
xharvest/models/hour.py
xharvest/models/preferences.py
xharvest/models/timeentries.py
xharvest/models/timesummary.py
xharvest/models/user.py
xharvest/models/week.py
xharvest/models/weekday.py
xharvest-0.8.0.data/data/share/applications/org.velvetkeyboad.xharvest.desktop
xharvest-0.8.0.dist-info/LICENSE
xharvest-0.8.0.dist-info/METADATA
xharvest-0.8.0.dist-info/WHEEL
xharvest-0.8.0.dist-info/entry_points.txt
xharvest-0.8.0.dist-info/top_level.txt
xharvest-0.8.0.dist-info/RECORD
