Metadata-Version: 2.1
Name: xharvest
Version: 0.8.0
Summary: Unofficial Harvest desktop for Linux
Home-page: https://gitlab.com/velvetkeyboad/py-xharvest
Author: Ramon Moraes
Author-email: ramonmoraes8080@gmail.com
License: MIT
Platform: UNKNOWN
Classifier: Development Status :: 4 - Beta
Classifier: Environment :: X11 Applications :: GTK
Classifier: License :: OSI Approved :: MIT License
Classifier: Operating System :: POSIX :: Linux
Classifier: Programming Language :: Python
Classifier: Programming Language :: Python :: 3
Classifier: Programming Language :: Python :: 3.6
Classifier: Programming Language :: Python :: 3.7
Classifier: Programming Language :: Python :: 3.8
Requires-Dist: pycairo (==1.19.1)
Requires-Dist: PyGObject (==3.34.0)
Requires-Dist: jeepney (==0.4.3)
Requires-Dist: keyring (==21.2.0)
Requires-Dist: keyring-jeepney (==0.2)
Requires-Dist: harvest-api (==0.3.0)
Provides-Extra: flatpak
Requires-Dist: keyrings.cryptfile (==1.3.4) ; extra == 'flatpak'
